[
  {
    "Tetel": "Rajzlap blokk A4 / 15ív - 160g",
    "Mennyiseg": "3",
    "Egysegar": "668.2",
    "Afa": "0.27",
    "Netto": "2004.6",
    "Brutto": "2545.84",
    "AfaOsszeg": "541.24",
    "Cikkszam": "E585440",
    "FaberMegnevezes": null,
    "DisplayText": "Rajzlap blokk A4 / 15ív - 160g | E585440"
  },
  {
    "Tetel": "Aquarell blokk A4 / 10ív; 224g",
    "Mennyiseg": "5",
    "Egysegar": "802.3",
    "Afa": "0.27",
    "Netto": "4011.5",
    "Brutto": "5094.61",
    "AfaOsszeg": "1083.11",
    "Cikkszam": "169618",
    "FaberMegnevezes": null,
    "DisplayText": "Aquarell blokk A4 / 10ív; 224g | 169618"
  },
  {
    "Tetel": "Aquarell blokk A3 / 10ív; 224g",
    "Mennyiseg": "3",
    "Egysegar": "1372.7",
    "Afa": "0.27",
    "Netto": "4118.1",
    "Brutto": "5229.99",
    "AfaOsszeg": "1111.89",
    "Cikkszam": "119065",
    "FaberMegnevezes": null,
    "DisplayText": "Aquarell blokk A3 / 10ív; 224g | 119065"
  },
  {
    "Tetel": "Művészceruza készlet / 17db",
    "Mennyiseg": "2",
    "Egysegar": "5656.8",
    "Afa": "0.27",
    "Netto": "11313.6",
    "Brutto": "14368.27",
    "AfaOsszeg": "3054.67",
    "Cikkszam": null,
    "FaberMegnevezes": null,
    "DisplayText": "Művészceruza készlet / 17db | "
  },
  {
    "Tetel": "Akvarellceruza készlet / 12db",
    "Mennyiseg": "2",
    "Egysegar": "6184.1",
    "Afa": "0.27",
    "Netto": "12368.2",
    "Brutto": "15707.61",
    "AfaOsszeg": "3339.41",
    "Cikkszam": null,
    "FaberMegnevezes": null,
    "DisplayText": "Akvarellceruza készlet / 12db | "
  },
  {
    "Tetel": "Radírbetét, precíziós / 4db",
    "Mennyiseg": "2",
    "Egysegar": "471.6",
    "Afa": "0.27",
    "Netto": "943.2",
    "Brutto": "1197.86",
    "AfaOsszeg": "254.66",
    "Cikkszam": "112112",
    "FaberMegnevezes": "Faber-Castell Art&Graphic Pitt pasztell színes ceruza 12db",
    "DisplayText": "Radírbetét, precíziós / 4db | 112112"
  },
  {
    "Tetel": "Művészceruza klt - Gift / 23db",
    "Mennyiseg": "1",
    "Egysegar": "7893.2",
    "Afa": "0.27",
    "Netto": "7893.2",
    "Brutto": "10024.36",
    "AfaOsszeg": "2131.16",
    "Cikkszam": null,
    "FaberMegnevezes": null,
    "DisplayText": "Művészceruza klt - Gift / 23db | "
  },
  {
    "Tetel": "Művészceruza, Gift set / 21db",
    "Mennyiseg": "1",
    "Egysegar": "7951.1",
    "Afa": "0.27",
    "Netto": "7951.1",
    "Brutto": "10097.9",
    "AfaOsszeg": "2146.8",
    "Cikkszam": "127024",
    "FaberMegnevezes": "Faber-Castell Creative Studio olajpasztell kréta készlet, 24db",
    "DisplayText": "Művészceruza, Gift set / 21db | 127024"
  },
  {
    "Tetel": "Művészfilc display, City / 8db",
    "Mennyiseg": "1",
    "Egysegar": "41572.8",
    "Afa": "0.27",
    "Netto": "41572.8",
    "Brutto": "52797.46",
    "AfaOsszeg": "11224.66",
    "Cikkszam": null,
    "FaberMegnevezes": null,
    "DisplayText": "Művészfilc display, City / 8db | "
  },
  {
    "Tetel": "Festővászon panel 30x40cm",
    "Mennyiseg": "30",
    "Egysegar": "546.5",
    "Afa": "0.27",
    "Netto": "16395",
    "Brutto": "20821.65",
    "AfaOsszeg": "4426.65",
    "Cikkszam": null,
    "FaberMegnevezes": null,
    "DisplayText": "Festővászon panel 30x40cm | "
  },
  {
    "Tetel": "R.tömb XL Marker A4 / 100ív",
    "Mennyiseg": "2",
    "Egysegar": "3086.1",
    "Afa": "0.27",
    "Netto": "6172.2",
    "Brutto": "7838.69",
    "AfaOsszeg": "1666.49",
    "Cikkszam": null,
    "FaberMegnevezes": null,
    "DisplayText": "R.tömb XL Marker A4 / 100ív | "
  },
  {
    "Tetel": "Minipack Mi-Teintes BT A4/10ív",
    "Mennyiseg": "5",
    "Egysegar": "1334.6",
    "Afa": "0.27",
    "Netto": "6673",
    "Brutto": "8474.71",
    "AfaOsszeg": "1801.71",
    "Cikkszam": "379280",
    "FaberMegnevezes": null,
    "DisplayText": "Minipack Mi-Teintes BT A4/10ív | 379280"
  },
  {
    "Tetel": "Minipack Mi-Teintes CT A4/10ív",
    "Mennyiseg": "5",
    "Egysegar": "1334.6",
    "Afa": "0.27",
    "Netto": "6673",
    "Brutto": "8474.71",
    "AfaOsszeg": "1801.71",
    "Cikkszam": null,
    "FaberMegnevezes": null,
    "DisplayText": "Minipack Mi-Teintes CT A4/10ív | "
  },
  {
    "Tetel": "R.tömb GRAD Mix.Med. B A5/20ív",
    "Mennyiseg": "2",
    "Egysegar": "1307",
    "Afa": "0.27",
    "Netto": "2614",
    "Brutto": "3319.78",
    "AfaOsszeg": "705.78",
    "Cikkszam": "114448",
    "FaberMegnevezes": null,
    "DisplayText": "R.tömb GRAD Mix.Med. B A5/20ív | 114448"
  },
  {
    "Tetel": "Sp.tömb XL Kraft A4 / 60ív",
    "Mennyiseg": "2",
    "Egysegar": "3086.1",
    "Afa": "0.27",
    "Netto": "6172.2",
    "Brutto": "7838.69",
    "AfaOsszeg": "1666.49",
    "Cikkszam": null,
    "FaberMegnevezes": null,
    "DisplayText": "Sp.tömb XL Kraft A4 / 60ív | "
  },
  {
    "Tetel": "Sp.tömb XL Hu& Acryl A3 / 30ív",
    "Mennyiseg": "1",
    "Egysegar": "5227.7",
    "Afa": "0.27",
    "Netto": "5227.7",
    "Brutto": "6639.18",
    "AfaOsszeg": "1411.48",
    "Cikkszam": null,
    "FaberMegnevezes": null,
    "DisplayText": "Sp.tömb XL Hu& Acryl A3 / 30ív | "
  },
  {
    "Tetel": "Sp.tömb XL Fluid MM. A4 / 30ív",
    "Mennyiseg": "2",
    "Egysegar": "3086.1",
    "Afa": "0.27",
    "Netto": "6172.2",
    "Brutto": "7838.69",
    "AfaOsszeg": "1666.49",
    "Cikkszam": null,
    "FaberMegnevezes": null,
    "DisplayText": "Sp.tömb XL Fluid MM. A4 / 30ív | "
  },
  {
    "Tetel": "Akvarellceruza klt - CE / 24db",
    "Mennyiseg": "1",
    "Egysegar": "1556.3",
    "Afa": "0.27",
    "Netto": "1556.3",
    "Brutto": "1976.5",
    "AfaOsszeg": "420.2",
    "Cikkszam": "114413",
    "FaberMegnevezes": null,
    "DisplayText": "Akvarellceruza klt - CE / 24db | 114413"
  },
  {
    "Tetel": "Akvarellceruza /24db fémdoboz",
    "Mennyiseg": "1",
    "Egysegar": "2830.6",
    "Afa": "0.27",
    "Netto": "2830.6",
    "Brutto": "3594.86",
    "AfaOsszeg": "764.26",
    "Cikkszam": null,
    "FaberMegnevezes": null,
    "DisplayText": "Akvarellceruza /24db fémdoboz | "
  },
  {
    "Tetel": "Ecsetszett vízfesték /6db",
    "Mennyiseg": "6",
    "Egysegar": "1456.3",
    "Afa": "0.27",
    "Netto": "8737.8",
    "Brutto": "11097.01",
    "AfaOsszeg": "2359.21",
    "Cikkszam": null,
    "FaberMegnevezes": null,
    "DisplayText": "Ecsetszett vízfesték /6db | "
  },
  {
    "Tetel": "Festővászon feszített 30x40cm",
    "Mennyiseg": "20",
    "Egysegar": "807.5",
    "Afa": "0.27",
    "Netto": "16150",
    "Brutto": "20510.5",
    "AfaOsszeg": "4360.5",
    "Cikkszam": null,
    "FaberMegnevezes": null,
    "DisplayText": "Festővászon feszített 30x40cm | "
  },
  {
    "Tetel": "Festővászon feszített 50X60cm",
    "Mennyiseg": "10",
    "Egysegar": "1430.2",
    "Afa": "0.27",
    "Netto": "14302",
    "Brutto": "18163.54",
    "AfaOsszeg": "3861.54",
    "Cikkszam": null,
    "FaberMegnevezes": null,
    "DisplayText": "Festővászon feszített 50X60cm | "
  },
  {
    "Tetel": "Hegyezőgép asztali - irodai",
    "Mennyiseg": "2",
    "Egysegar": "1255.7",
    "Afa": "0.27",
    "Netto": "2511.4",
    "Brutto": "3189.48",
    "AfaOsszeg": "678.08",
    "Cikkszam": null,
    "FaberMegnevezes": null,
    "DisplayText": "Hegyezőgép asztali - irodai | "
  },
  {
    "Tetel": "Vágókés Univerzális \"S\" PRO",
    "Mennyiseg": "6",
    "Egysegar": "369.3",
    "Afa": "0.27",
    "Netto": "2215.8",
    "Brutto": "2814.07",
    "AfaOsszeg": "598.27",
    "Cikkszam": null,
    "FaberMegnevezes": null,
    "DisplayText": "Vágókés Univerzális \"S\" PRO | "
  },
  {
    "Tetel": "Vonalzó fém PRO - 50 cm",
    "Mennyiseg": "2",
    "Egysegar": "897.4",
    "Afa": "0.27",
    "Netto": "1794.8",
    "Brutto": "2279.4",
    "AfaOsszeg": "484.6",
    "Cikkszam": null,
    "FaberMegnevezes": null,
    "DisplayText": "Vonalzó fém PRO - 50 cm | "
  },
  {
    "Tetel": "Sketch Marker, h.szög / 36db",
    "Mennyiseg": "2",
    "Egysegar": "3304.395",
    "Afa": "0.27",
    "Netto": "6608.79",
    "Brutto": "8393.16",
    "AfaOsszeg": "1784.37",
    "Cikkszam": null,
    "FaberMegnevezes": null,
    "DisplayText": "Sketch Marker, h.szög / 36db | "
  },
  {
    "Tetel": "Sketch Marker, h.szög / 60db",
    "Mennyiseg": "1",
    "Egysegar": "4969.512",
    "Afa": "0.27",
    "Netto": "4969.51",
    "Brutto": "6311.28",
    "AfaOsszeg": "1341.77",
    "Cikkszam": null,
    "FaberMegnevezes": null,
    "DisplayText": "Sketch Marker, h.szög / 60db | "
  },
  {
    "Tetel": "Vágólap öngyógyuló A4 / Zöld",
    "Mennyiseg": "2",
    "Egysegar": "1044.3",
    "Afa": "0.27",
    "Netto": "2088.6",
    "Brutto": "2652.52",
    "AfaOsszeg": "563.92",
    "Cikkszam": null,
    "FaberMegnevezes": null,
    "DisplayText": "Vágólap öngyógyuló A4 / Zöld | "
  },
  {
    "Tetel": "Sz.ceruza klt. fém dob. / 36db",
    "Mennyiseg": "3",
    "Egysegar": "13155.7",
    "Afa": "0.27",
    "Netto": "39467.1",
    "Brutto": "50123.22",
    "AfaOsszeg": "10656.12",
    "Cikkszam": null,
    "FaberMegnevezes": null,
    "DisplayText": "Sz.ceruza klt. fém dob. / 36db | "
  },
  {
    "Tetel": "Színesceruza, fémdob. / 24db",
    "Mennyiseg": "2",
    "Egysegar": "4725",
    "Afa": "0.27",
    "Netto": "9450",
    "Brutto": "12001.5",
    "AfaOsszeg": "2551.5",
    "Cikkszam": null,
    "FaberMegnevezes": null,
    "DisplayText": "Színesceruza, fémdob. / 24db | "
  },
  {
    "Tetel": "Akvarell-színesceruza / 12db",
    "Mennyiseg": "5",
    "Egysegar": "998.9",
    "Afa": "0.27",
    "Netto": "4994.5",
    "Brutto": "6343.02",
    "AfaOsszeg": "1348.52",
    "Cikkszam": null,
    "FaberMegnevezes": null,
    "DisplayText": "Akvarell-színesceruza / 12db | "
  },
  {
    "Tetel": "G.ceruza, fém dob. Matt / 6db",
    "Mennyiseg": "4",
    "Egysegar": "2229.5",
    "Afa": "0.27",
    "Netto": "8918",
    "Brutto": "11325.86",
    "AfaOsszeg": "2407.86",
    "Cikkszam": null,
    "FaberMegnevezes": null,
    "DisplayText": "G.ceruza, fém dob. Matt / 6db | "
  },
  {
    "Tetel": "Színesceruza / 100db",
    "Mennyiseg": "6",
    "Egysegar": "9647.7",
    "Afa": "0.27",
    "Netto": "57886.2",
    "Brutto": "73515.47",
    "AfaOsszeg": "15629.27",
    "Cikkszam": null,
    "FaberMegnevezes": null,
    "DisplayText": "Színesceruza / 100db | "
  },
  {
    "Tetel": "Színesceruza / 12db",
    "Mennyiseg": "6",
    "Egysegar": "1158",
    "Afa": "0.27",
    "Netto": "6948",
    "Brutto": "8823.96",
    "AfaOsszeg": "1875.96",
    "Cikkszam": null,
    "FaberMegnevezes": null,
    "DisplayText": "Színesceruza / 12db | "
  },
  {
    "Tetel": "Színesceruza, testszín / 12db",
    "Mennyiseg": "4",
    "Egysegar": "1158",
    "Afa": "0.27",
    "Netto": "4632",
    "Brutto": "5882.64",
    "AfaOsszeg": "1250.64",
    "Cikkszam": null,
    "FaberMegnevezes": null,
    "DisplayText": "Színesceruza, testszín / 12db | "
  },
  {
    "Tetel": "Sz.ceruza - pencil roll / 72db",
    "Mennyiseg": "4",
    "Egysegar": "9647.7",
    "Afa": "0.27",
    "Netto": "38590.8",
    "Brutto": "49010.32",
    "AfaOsszeg": "10419.52",
    "Cikkszam": null,
    "FaberMegnevezes": null,
    "DisplayText": "Sz.ceruza - pencil roll / 72db | "
  },
  {
    "Tetel": "Színesceruza / 36db",
    "Mennyiseg": "2",
    "Egysegar": "3473.9",
    "Afa": "0.27",
    "Netto": "6947.8",
    "Brutto": "8823.71",
    "AfaOsszeg": "1875.91",
    "Cikkszam": null,
    "FaberMegnevezes": null,
    "DisplayText": "Színesceruza / 36db | "
  },
  {
    "Tetel": "Filctollkészlet / 10db",
    "Mennyiseg": "1",
    "Egysegar": "1658",
    "Afa": "0.27",
    "Netto": "1658",
    "Brutto": "2105.66",
    "AfaOsszeg": "447.66",
    "Cikkszam": null,
    "FaberMegnevezes": null,
    "DisplayText": "Filctollkészlet / 10db | "
  },
  {
    "Tetel": "Filctollkészlet / 20db",
    "Mennyiseg": "1",
    "Egysegar": "3315.9",
    "Afa": "0.27",
    "Netto": "3315.9",
    "Brutto": "4211.19",
    "AfaOsszeg": "895.29",
    "Cikkszam": null,
    "FaberMegnevezes": null,
    "DisplayText": "Filctollkészlet / 20db | "
  },
  {
    "Tetel": "Szénceruza, olajm. / 199 soft",
    "Mennyiseg": "6",
    "Egysegar": "376.1",
    "Afa": "0.27",
    "Netto": "2256.6",
    "Brutto": "2865.88",
    "AfaOsszeg": "609.28",
    "Cikkszam": null,
    "FaberMegnevezes": null,
    "DisplayText": "Szénceruza, olajm. / 199 soft | "
  },
  {
    "Tetel": "G.ceruza fémd. Art / 12db",
    "Mennyiseg": "10",
    "Egysegar": "3005.7",
    "Afa": "0.27",
    "Netto": "30057",
    "Brutto": "38172.39",
    "AfaOsszeg": "8115.39",
    "Cikkszam": null,
    "FaberMegnevezes": null,
    "DisplayText": "G.ceruza fémd. Art / 12db | "
  },
  {
    "Tetel": "Nyomósirón betét, 0.35mm / B",
    "Mennyiseg": "3",
    "Egysegar": "248.9",
    "Afa": "0.27",
    "Netto": "746.7",
    "Brutto": "948.31",
    "AfaOsszeg": "201.61",
    "Cikkszam": null,
    "FaberMegnevezes": null,
    "DisplayText": "Nyomósirón betét, 0.35mm / B | "
  },
  {
    "Tetel": "Olajpasztellkréta / 12db",
    "Mennyiseg": "2",
    "Egysegar": "1046.6",
    "Afa": "0.27",
    "Netto": "2093.2",
    "Brutto": "2658.36",
    "AfaOsszeg": "565.16",
    "Cikkszam": null,
    "FaberMegnevezes": null,
    "DisplayText": "Olajpasztellkréta / 12db | "
  },
  {
    "Tetel": "Töltőc.-betét 2.0mm / 3B 10db",
    "Mennyiseg": "2",
    "Egysegar": "1067",
    "Afa": "0.27",
    "Netto": "2134",
    "Brutto": "2710.18",
    "AfaOsszeg": "576.18",
    "Cikkszam": null,
    "FaberMegnevezes": null,
    "DisplayText": "Töltőc.-betét 2.0mm / 3B 10db | "
  },
  {
    "Tetel": "Nyomósirón 0.35mm / sötétzöld",
    "Mennyiseg": "2",
    "Egysegar": "972.7",
    "Afa": "0.27",
    "Netto": "1945.4",
    "Brutto": "2470.66",
    "AfaOsszeg": "525.26",
    "Cikkszam": null,
    "FaberMegnevezes": null,
    "DisplayText": "Nyomósirón 0.35mm / sötétzöld | "
  },
  {
    "Tetel": "Nyomósirón 0.7mm / sötétzöld",
    "Mennyiseg": "2",
    "Egysegar": "972.7",
    "Afa": "0.27",
    "Netto": "1945.4",
    "Brutto": "2470.66",
    "AfaOsszeg": "525.26",
    "Cikkszam": null,
    "FaberMegnevezes": null,
    "DisplayText": "Nyomósirón 0.7mm / sötétzöld | "
  },
  {
    "Tetel": "Tűfilc 0.4mm / 10db",
    "Mennyiseg": "2",
    "Egysegar": "964.8",
    "Afa": "0.27",
    "Netto": "1929.6",
    "Brutto": "2450.59",
    "AfaOsszeg": "520.99",
    "Cikkszam": null,
    "FaberMegnevezes": null,
    "DisplayText": "Tűfilc 0.4mm / 10db | "
  },
  {
    "Tetel": "Tűfilc 0.4mm / 20db",
    "Mennyiseg": "2",
    "Egysegar": "1929.5",
    "Afa": "0.27",
    "Netto": "3859",
    "Brutto": "4900.93",
    "AfaOsszeg": "1041.93",
    "Cikkszam": null,
    "FaberMegnevezes": null,
    "DisplayText": "Tűfilc 0.4mm / 20db | "
  },
  {
    "Tetel": "Tűfilc 0.4mm / 30db",
    "Mennyiseg": "2",
    "Egysegar": "2894.3",
    "Afa": "0.27",
    "Netto": "5788.6",
    "Brutto": "7351.52",
    "AfaOsszeg": "1562.92",
    "Cikkszam": null,
    "FaberMegnevezes": null,
    "DisplayText": "Tűfilc 0.4mm / 30db | "
  },
  {
    "Tetel": "Jelölőfilc mosodai / fekete",
    "Mennyiseg": "15",
    "Egysegar": "244.3",
    "Afa": "0.27",
    "Netto": "3664.5",
    "Brutto": "4653.92",
    "AfaOsszeg": "989.42",
    "Cikkszam": null,
    "FaberMegnevezes": null,
    "DisplayText": "Jelölőfilc mosodai / fekete | "
  },
  {
    "Tetel": "Tűfilc - 0.8mm / fekete",
    "Mennyiseg": "10",
    "Egysegar": "501.1",
    "Afa": "0.27",
    "Netto": "5011",
    "Brutto": "6363.97",
    "AfaOsszeg": "1352.97",
    "Cikkszam": null,
    "FaberMegnevezes": null,
    "DisplayText": "Tűfilc - 0.8mm / fekete | "
  },
  {
    "Tetel": "Fineliner \"S\" / 199 black",
    "Mennyiseg": "6",
    "Egysegar": "480.7",
    "Afa": "0.27",
    "Netto": "2884.2",
    "Brutto": "3662.93",
    "AfaOsszeg": "778.73",
    "Cikkszam": null,
    "FaberMegnevezes": null,
    "DisplayText": "Fineliner \"S\" / 199 black | "
  },
  {
    "Tetel": "Tolltartó, tekercses (üres)",
    "Mennyiseg": "2",
    "Egysegar": "4009.1",
    "Afa": "0.27",
    "Netto": "8018.2",
    "Brutto": "10183.11",
    "AfaOsszeg": "2164.91",
    "Cikkszam": null,
    "FaberMegnevezes": null,
    "DisplayText": "Tolltartó, tekercses (üres) | "
  },
  {
    "Tetel": "Dörzshegyező, többrétegű",
    "Mennyiseg": "2",
    "Egysegar": "567",
    "Afa": "0.27",
    "Netto": "1134",
    "Brutto": "1440.18",
    "AfaOsszeg": "306.18",
    "Cikkszam": null,
    "FaberMegnevezes": null,
    "DisplayText": "Dörzshegyező, többrétegű | "
  },
  {
    "Tetel": "Akril festőkészlet / 18db",
    "Mennyiseg": "2",
    "Egysegar": "3534.1",
    "Afa": "0.27",
    "Netto": "7068.2",
    "Brutto": "8976.61",
    "AfaOsszeg": "1908.41",
    "Cikkszam": null,
    "FaberMegnevezes": null,
    "DisplayText": "Akril festőkészlet / 18db | "
  },
  {
    "Tetel": "Olajfesték készlet / 24db",
    "Mennyiseg": "2",
    "Egysegar": "5125",
    "Afa": "0.27",
    "Netto": "10250",
    "Brutto": "13017.5",
    "AfaOsszeg": "2767.5",
    "Cikkszam": null,
    "FaberMegnevezes": null,
    "DisplayText": "Olajfesték készlet / 24db | "
  },
  {
    "Tetel": "Filctoll kastély / 24db",
    "Mennyiseg": "3",
    "Egysegar": "854.5",
    "Afa": "0.27",
    "Netto": "2563.5",
    "Brutto": "3255.65",
    "AfaOsszeg": "692.15",
    "Cikkszam": null,
    "FaberMegnevezes": null,
    "DisplayText": "Filctoll kastély / 24db | "
  },
  {
    "Tetel": "Radír forgácsmentes / s.zöld",
    "Mennyiseg": "6",
    "Egysegar": "178.4",
    "Afa": "0.27",
    "Netto": "1070.4",
    "Brutto": "1359.41",
    "AfaOsszeg": "289.01",
    "Cikkszam": null,
    "FaberMegnevezes": null,
    "DisplayText": "Radír forgácsmentes / s.zöld | "
  }
]